{
  "$schema": "https://mintlify.com/schema.json",
  "name": "HYPIQ Documentation",
  "logo": {
    "dark": "/HYPIQ-logo-white.png",
    "light": "/HYPIQ-logo-white.png"
  },
  "favicon": "/HYPIQ-logo-white.png",
  "colors": {
    "primary": "#4ade80",
    "light": "#4ade80",
    "dark": "#22c55e",
    "anchors": {
      "from": "#4ade80",
      "to": "#22c55e"
    }
  },


  "navigation": [
    {
      "group": "Platform",
      "pages": [
        "index",
        "platform/overview"
      ]
    },
    {
      "group": "Prediction Markets",
      "pages": [
        "prediction/earn"
      ]
    },
    {
      "group": "✨ Brand Kit",
      "pages": [
        "brand/logos-assets",
        "brand/colors",
        "brand/typography-iconography"
      ]
    }
  ],
  "footerSocials": {
    "twitter": "https://twitter.com/hypiq_finance",
    "linkedin": "https://linkedin.com/company/hypiq"
  },
  "backgroundImage": "/docs/background.png",
  "theme": "quill",
  "icons": {
    "library": "lucide"
  }
}